aview_cmd_builder_package_olodiman11/__init__.py
aview_cmd_builder_package_olodiman11/aview_cmd_builder.py
aview_cmd_builder-0.0.1.dist-info/LICENSE
aview_cmd_builder-0.0.1.dist-info/METADATA
aview_cmd_builder-0.0.1.dist-info/WHEEL
aview_cmd_builder-0.0.1.dist-info/top_level.txt
aview_cmd_builder-0.0.1.dist-info/RECORD
